ryan_lang-0.2.4.dist-info/METADATA
ryan_lang-0.2.4.dist-info/WHEEL
ryan/__init__.py
ryan/ryan.cpython-39-x86_64-linux-gnu.so
ryan_lang-0.2.4.dist-info/RECORD
