Metadata-Version: 2.1
Name: ryan-lang
Version: 0.2.4
Classifier: Programming Language :: Rust
Classifier: License :: OSI Approved :: MIT License
Requires-Dist: cffi
Summary: Ryan: a configuration language for the practical programmer
Keywords: cli,parser,json,serde,serialization
Author: Pedro Bittencorut Arruda <pedrobittencourt3@gmail.com>
Author-email: Pedro B. Arruda <pedrobittencourt3@gmail.com>
License: MIT
Requires-Python: >=3.7
Project-URL: Homepage, https://github.com/tokahuke/ryan
